adap_exercice/__init__.py
adap_exercice/__main__.py
adap_exercice/class_define.py
adap_exercice/latex_fin.py
adap_exercice/latex_q1.py
adap_exercice/latex_q2.py
adap_exercice/latex_q3.py
adap_exercice/latex_q4.py
adap_exercice/latex_q5.py
adap_exercice/latex_q6.py
adap_exercice/main.py
adap_exercice/resolution.py
adap_exercice-0.2.0.dist-info/entry_points.txt
adap_exercice-0.2.0.dist-info/WHEEL
adap_exercice-0.2.0.dist-info/METADATA
adap_exercice-0.2.0.dist-info/RECORD
