Metadata-Version: 2.1
Name: adap-exercice
Version: 0.2.0
Summary: Library to create a tex and pdf file of an exercice of economics which can be modified by the user
Author: Mathieu
Author-email: mathieuveron@outlook.fr
Requires-Python: >=3.11,<4.0
Classifier: Programming Language :: Python :: 3
Classifier: Programming Language :: Python :: 3.11
Requires-Dist: matplotlib (>=3.6.2,<4.0.0)
Requires-Dist: sympy (>=1.11.1,<2.0.0)
Requires-Dist: typer[all] (>=0.7.0,<0.8.0)
